setup.py
src/eparser/__init__.py
src/eparser/parsers.py
src/eparser/tests.py
src/eparser.egg-info/PKG-INFO
src/eparser.egg-info/SOURCES.txt
src/eparser.egg-info/dependency_links.txt
src/eparser.egg-info/top_level.txt