Metadata-Version: 1.0
Name: eparser
Version: 1.0.0
Summary: Generic Email-Address List Parser
Home-page: https://github.com/HireIQ/email-address-parser
Author: Alex Milstead
Author-email: alex@amilstead.com
License: MIT License
Platform: UNKNOWN
